[{"url": "https://www.kuaishou.com/short-video/3xrve76yvvqbz9m", "title": "总书记为中央企业工作指明方向"}, {"url": "https://www.kuaishou.com/short-video/3xfg3yfhengn2j6", "title": "北京调整住房限购政策"}, {"url": "https://www.kuaishou.com/short-video/3xcrsz63hy7qr6s", "title": "日本高官拥核言论绝非孤立事件"}, {"url": "https://www.kuaishou.com/short-video/3x38ttbqvav2454", "title": "我国冰雪产业规模将破万亿元"}, {"url": "https://www.kuaishou.com/short-video/3xfxnsxvsxsdhzy", "title": "东莞黑老大猴子被判无期"}, {"url": "https://www.kuaishou.com/short-video/3x8me6b7pckr5ky", "title": "日本夫妻在桑拿房被活活蒸死"}, {"url": "https://www.kuaishou.com/short-video/3x2ee52ehqug634", "title": "王峻被查"}, {"url": "https://www.kuaishou.com/short-video/3xxmm4q4s67i882", "title": "混血小孩爱上哈尔滨锅包肉"}, {"url": "https://www.kuaishou.com/short-video/3x4tu2n2y83qryg", "title": "第3届金声奖名场面回顾"}, {"url": "https://www.kuaishou.com/short-video/3xq4j8v5hmrazfu", "title": "李延年涉违纪违法被查"}, {"url": "https://www.kuaishou.com/short-video/3xfuwd6dsr2ei32", "title": "土耳其现近700个巨大天坑"}, {"url": "https://www.kuaishou.com/short-video/3xjtaj8n9r88wgc", "title": "江西坠塘案遇难遗体已送往殡仪馆"}, {"url": "https://www.kuaishou.com/short-video/3xwb5v4g6ad9t9q", "title": "官方正式回应“吸毒记录封存”"}, {"url": "https://www.kuaishou.com/short-video/3xae4nbiu8bdybi", "title": "江西车辆坠塘事故家长发声"}, {"url": "https://www.kuaishou.com/short-video/3xbdauw57qz2q49", "title": "情侣版萝卜纸巾挑战"}, {"url": "https://www.kuaishou.com/short-video/3xisfm923krfd84", "title": "故宫鉴定泰斗杨臣彬"}, {"url": "https://www.kuaishou.com/short-video/3xk9zueqwgyt7qa", "title": "追你要钱也要颜那我不追了"}, {"url": "https://www.kuaishou.com/short-video/3xd74sziyyyad56", "title": "中央纪委印发新型腐败证据指引"}, {"url": "https://www.kuaishou.com/short-video/3xvuh6qscxstpey", "title": "国台办谈两岸携手发展机遇"}, {"url": "https://www.kuaishou.com/short-video/3xqabg77gcf3axm", "title": "iPhone18系列首发A20芯片"}, {"url": "https://www.kuaishou.com/short-video/3xuv9ajunz42ih9", "title": "金饰克价涨至1411元"}, {"url": "https://www.kuaishou.com/short-video/3xpzxm73iayu9x4", "title": "广东女子出售260元每克黄金"}, {"url": "https://www.kuaishou.com/short-video/3x5dsc56fg3757a", "title": "银价已暴涨近140%"}, {"url": "https://www.kuaishou.com/short-video/3xv8cxbp9hnynms", "title": "齐齐哈尔一恶势力团伙多人获刑"}, {"url": "https://www.kuaishou.com/short-video/3x9efz3fic3udvw", "title": "享福了"}, {"url": "https://www.kuaishou.com/short-video/3x2qtv74fbjt8ys", "title": "赵露思经纪人李炜发文"}, {"url": "https://www.kuaishou.com/short-video/3xesdvatgqfpwik", "title": "江西车辆落水事件涉事幼儿园停课"}, {"url": "https://www.kuaishou.com/short-video/3x5ju8jyxwau6cg", "title": "茅台价格全线上涨"}, {"url": "https://www.kuaishou.com/short-video/3xs79w29sgb33he", "title": "小米17Ultra致敬iPhone4按键设计"}, {"url": "https://www.kuaishou.com/short-video/3x2dwexd9dzdujk", "title": "美国斩杀线真实存在吗"}, {"url": "https://www.kuaishou.com/short-video/3xfmxb643mvs9zc", "title": "测测你结婚的年龄"}, {"url": "https://www.kuaishou.com/short-video/3xf4jesb9saxfw4", "title": "心理委员提醒你"}, {"url": "https://www.kuaishou.com/short-video/3xqaqjixkuenc9q", "title": "期末学生的精神状态"}, {"url": "https://www.kuaishou.com/short-video/3xb2j7d8ei25wp2", "title": "著名导演翟俊杰去世"}, {"url": "https://www.kuaishou.com/short-video/3xdqvikt3v7z7t6", "title": "美国斩杀线有多残酷"}, {"url": "https://www.kuaishou.com/short-video/3x8kritvq36xsea", "title": "浏阳烟花出品必是细糠"}, {"url": "https://www.kuaishou.com/short-video/3x7cce5rve7sjpy", "title": "南京大屠杀幸存者证言"}, {"url": "https://www.kuaishou.com/short-video/3xz7w99pe6fktfw", "title": "俄军用乌军无人机装饰新年枞树"}, {"url": "https://www.kuaishou.com/short-video/3xxhmhwfguvqhw2", "title": "国家提前下达20408万元"}, {"url": "https://www.kuaishou.com/short-video/3x254wp5cybhspg", "title": "俞敏洪已敲定东方甄选接班人"}, {"url": "https://www.kuaishou.com/short-video/3xmar5zwzx5nd9i", "title": "陆毅 14岁少女的成长仪式"}, {"url": "https://www.kuaishou.com/short-video/3xpwqer9uhnzine", "title": "防返贫动态监测系统"}, {"url": "https://www.kuaishou.com/short-video/3xrhwyf4a2pmzig", "title": "为了你我犯下罪"}, {"url": "https://www.kuaishou.com/short-video/3xqy84siy4iyya2", "title": "江西坠塘案园长老公已被警方控制"}, {"url": "https://www.kuaishou.com/short-video/3xha4d7zauyfczs", "title": "雪后哈尔滨游客盛赞"}, {"url": "https://www.kuaishou.com/short-video/3xe3hcvqbfkkt82", "title": "江西落水事故车是幼儿园长私家车"}, {"url": "https://www.kuaishou.com/short-video/3x4uvu3vhjkn2ys", "title": "湘超决赛你支持哪队"}, {"url": "https://www.kuaishou.com/short-video/3x7ybzvhsi5rqsm", "title": "冉莹颖儿子打生长激素长高8厘米"}, {"url": "https://www.kuaishou.com/short-video/3x2qj7mq2nxeejs", "title": "安徽27天婴儿治黄疸死亡"}, {"url": "https://www.kuaishou.com/short-video/3x8ck7q7db7vg4s", "title": "坚持做强国内大循环"}, {"url": "https://www.kuaishou.com/short-video/3x33ypr89tebvg6", "title": "一组数据看我国区域外贸稳中有进"}, {"url": "https://www.kuaishou.com/short-video/3xktsrkewxbe3r6", "title": "外交部称暴露“再军事化”野心"}, {"url": "https://www.kuaishou.com/short-video/3xx5vuv9g46drpy", "title": "著名导演翟俊杰去世"}, {"url": "https://www.kuaishou.com/short-video/3x4nr72rdrvnkuk", "title": "江西落水事故提示安全问题应重视"}, {"url": "https://www.kuaishou.com/short-video/3xuzhff8chrnfdk", "title": "郑丽文回呛国民党挡军购"}, {"url": "https://www.kuaishou.com/short-video/3x2mm6adbgcgd5m", "title": "陈辰获金声奖优秀主持人"}, {"url": "https://www.kuaishou.com/short-video/3x7vy2r2ckhvnkc", "title": "中信建投女总监受贿获刑"}, {"url": "https://www.kuaishou.com/short-video/3xh2i6gmypiyz5a", "title": "深度剖析美国斩杀线"}, {"url": "https://www.kuaishou.com/short-video/3x69k5336jcr7vq", "title": "园长丈夫配合调查车辆坠塘事故"}, {"url": "https://www.kuaishou.com/short-video/3x92xcirzpf4cpk", "title": "宁夏四代军人传承家风"}, {"url": "https://www.kuaishou.com/short-video/3x7i28mh5785msq", "title": "外交部敦促日方履行核安全责任"}, {"url": "https://www.kuaishou.com/short-video/3x3tx7mcikqymzg", "title": "茅台价格全线上涨"}, {"url": "https://www.kuaishou.com/short-video/3xits3fa9yg5edi", "title": "看懂斩杀线庆幸生活在中国"}, {"url": "https://www.kuaishou.com/short-video/3xt2ix7mccceryu", "title": "巴第四艘麒麟级潜艇武汉下水"}, {"url": "https://www.kuaishou.com/short-video/3xm3ciuqtqqe8ta", "title": "金价今年已50次改写历史新高"}, {"url": "https://www.kuaishou.com/short-video/3xag8cccxrceaxa", "title": "北平锋评台美军售争议"}, {"url": "https://www.kuaishou.com/short-video/3xwdg3axq9t8tdq", "title": "专家谈俄中将莫斯科遇袭身亡"}, {"url": "https://www.kuaishou.com/short-video/3xbtjjswybgwtq4", "title": "康定回应23岁硕士生徒步去世"}, {"url": "https://www.kuaishou.com/short-video/3xf6g8eyv7p3b4s", "title": "A股全市场超4100只个股上涨"}, {"url": "https://www.kuaishou.com/short-video/3xcej2ik4sm9aa4", "title": "志愿军老兵：手脚全无也不后悔"}, {"url": "https://www.kuaishou.com/short-video/3xf5msitss87uii", "title": "为了你我犯下罪手势舞"}, {"url": "https://www.kuaishou.com/short-video/3xpnyd6qeax4k8i", "title": "人民币现金收付新规明年施行"}, {"url": "https://www.kuaishou.com/short-video/3xe3gxb6qkamapu", "title": "日本夫妻在桑拿房被活活蒸死"}, {"url": "https://www.kuaishou.com/short-video/3xzkhwr6ihkfmpk", "title": "印度医生殴打病人引众怒"}, {"url": "https://www.kuaishou.com/short-video/3xcikb9cnjbm8w2", "title": "敢穿越台湾海峡的航母只有解放军"}, {"url": "https://www.kuaishou.com/short-video/3xm3pnwme387xhe", "title": "美国从中产到流浪只差一步"}, {"url": "https://www.kuaishou.com/short-video/3xwbswypt7czhgk", "title": "泰国士兵展示缴获的战利品"}, {"url": "https://www.kuaishou.com/short-video/3x6767w4sxir5fc", "title": "专家：日本试图在地理上围堵中国"}, {"url": "https://www.kuaishou.com/short-video/3xmrfrwvdti49t6", "title": "国台办回应台民意机构弹劾赖清德"}, {"url": "https://www.kuaishou.com/short-video/3x8bbuigecn7nns", "title": "克林顿再次回应卷入爱泼斯坦案"}, {"url": "https://www.kuaishou.com/short-video/3x9pei4bsjbem8e", "title": "泰军在柬赌场发现狮子黑熊"}, {"url": "https://www.kuaishou.com/short-video/3xjzvvhxqqzkq4q", "title": "快船大胜火箭"}, {"url": "https://www.kuaishou.com/short-video/3xm5eamr3476buq", "title": "国际社会应坚决阻遏日本拥核冲动"}, {"url": "https://www.kuaishou.com/short-video/3x8pfvisn5q3tvy", "title": "京东回应法国仓库失窃事件"}, {"url": "https://www.kuaishou.com/short-video/3xsvpcs8d4nf33k", "title": "女网友贷款打赏男主播42万"}, {"url": "https://www.kuaishou.com/short-video/3xdsbuxmdpqeaes", "title": "周深跨年夜彩排全情投入"}, {"url": "https://www.kuaishou.com/short-video/3xigg3uuv65wn9c", "title": "胡兵薛佳凝跨越二十年的重逢"}, {"url": "https://www.kuaishou.com/short-video/3xdib9rtefpv45q", "title": "江西落水事故车是幼儿园长私家车"}, {"url": "https://www.kuaishou.com/short-video/3x9b3v4p59w6cp4", "title": "巴山楚水凄凉地 一秒转身上压力"}, {"url": "https://www.kuaishou.com/short-video/3xtgv7au76r2ukc", "title": "大冰的新年树洞好暖心"}, {"url": "https://www.kuaishou.com/short-video/3xa7qi9vtnmcrks", "title": "湖人惨败太阳"}, {"url": "https://www.kuaishou.com/short-video/3xpr2j9jsg8fj62", "title": "江西坠塘事故车辆警方通报非校车"}, {"url": "https://www.kuaishou.com/short-video/3xdjt7kxiq7egps", "title": "冬日摇"}, {"url": "https://www.kuaishou.com/short-video/3xckxr6r3nm7gdg", "title": "大沈阳是我的家乡"}, {"url": "https://www.kuaishou.com/short-video/3x9mj9ea6k3pjrw", "title": "口罩在车内突发“自燃”"}, {"url": "https://www.kuaishou.com/short-video/3x6at6yktt2t342", "title": "我国禁毒工作没有任何松懈"}, {"url": "https://www.kuaishou.com/short-video/3xu34eydn226hvu", "title": "家有小丑"}, {"url": "https://www.kuaishou.com/short-video/3x7fck39iuzmvjs", "title": "萝卜纸巾的优等生来了"}, {"url": "https://www.kuaishou.com/short-video/3xkts4rx7jgue56", "title": "活塞136比127国王"}, {"url": "https://www.kuaishou.com/short-video/3xuugn8g3mdkqiu", "title": "相遇已是上上签"}, {"url": "https://www.kuaishou.com/short-video/3xhxqi7e6j3wde6", "title": "憋笑挑战逐渐离谱"}, {"url": "https://www.kuaishou.com/short-video/3x9v2xhagsffdt9", "title": "800万人联署支持弹劾赖清德"}, {"url": "https://www.kuaishou.com/short-video/3x4xe6gfbdgrz24", "title": "斯奎奇大王牢A是谁"}, {"url": "https://www.kuaishou.com/short-video/3xsietr456ym9qc", "title": "江西车辆落水事故园方失联"}, {"url": "https://www.kuaishou.com/short-video/3xkda95uxw2ztn2", "title": "洋芋粑洋芋粑不敢带你回老家"}, {"url": "https://www.kuaishou.com/short-video/3xrntidty5h6d2s", "title": "世界这么大还是遇见你"}, {"url": "https://www.kuaishou.com/short-video/3x4sw26gyc4nuve", "title": "小米17Ultra光学变焦升级"}, {"url": "https://www.kuaishou.com/short-video/3xtjgbcdjcq33g4", "title": "谁还没拥有光遇瑞雪斗篷"}, {"url": "https://www.kuaishou.com/short-video/3x72g6x6atkrwx9", "title": "警惕日本军国主义死灰复燃"}, {"url": "https://www.kuaishou.com/short-video/3x8dbu3m3wubnfm", "title": "美食界真神相继现身"}, {"url": "https://www.kuaishou.com/short-video/3x7sxqzhk3bweia", "title": "谁是卧底大挑战"}, {"url": "https://www.kuaishou.com/short-video/3xmiv7i6jdem36y", "title": "官方正式回应“吸毒记录封存”"}, {"url": "https://www.kuaishou.com/short-video/3xjy3v9gtc9stp6", "title": "碧蓝航线cos"}, {"url": "https://www.kuaishou.com/short-video/3x88eketr37zfry", "title": "冬日摇"}, {"url": "https://www.kuaishou.com/short-video/3x6cbvtue6bc8vm", "title": "冯忠华任广州市委书记"}, {"url": "https://www.kuaishou.com/short-video/3xkgzkgkq594k8u", "title": "江西落水事故车辆属当地幼儿园"}, {"url": "https://www.kuaishou.com/short-video/3xbcuhdwdxkmwci", "title": "小猴子也来参加艺术节"}, {"url": "https://www.kuaishou.com/short-video/3xwafxyzirgdurm", "title": "江湖天涯客翻唱"}, {"url": "https://www.kuaishou.com/short-video/3xef3euqk7uyr8q", "title": "咱的安全感早被国家兜底了"}, {"url": "https://www.kuaishou.com/short-video/3xi5wwxphxx82uw", "title": "国台办：欢迎台湾同胞到大陆"}, {"url": "https://www.kuaishou.com/short-video/3x6cjmcutdhze49", "title": "电报创始人承诺其子女可继承遗产"}, {"url": "https://www.kuaishou.com/short-video/3xcxz9az4wy9eas", "title": "国台办：祖国统一势不可挡"}, {"url": "https://www.kuaishou.com/short-video/3xvncbpvxz8q3bk", "title": "王小平受贿案二审宣判"}, {"url": "https://www.kuaishou.com/short-video/3xv95bsgzhbenni", "title": "台湾小公司变身军火大亨遭质疑"}, {"url": "https://www.kuaishou.com/short-video/3xs2x9csca6kffm", "title": "洛阳一仓库突发大火"}, {"url": "https://www.kuaishou.com/short-video/3xawik5c3acish9", "title": "终于轮到我拍日照金山啦"}, {"url": "https://www.kuaishou.com/short-video/3xsud75n9dnjqzm", "title": "国台办批美为“台独”搭台"}, {"url": "https://www.kuaishou.com/short-video/3x7mpi2h4ntz4k9", "title": "北京跨晚第三波阵容官宣"}, {"url": "https://www.kuaishou.com/short-video/3xhwszgiy9jh53a", "title": "“台独”分裂势力难逃法律制裁"}, {"url": "https://www.kuaishou.com/short-video/3xs7kq32zhkrtpc", "title": "美国宾州一养老院发生燃气爆炸"}, {"url": "https://www.kuaishou.com/short-video/3xmu2fzf788u542", "title": "2025中国航天高燃时刻"}, {"url": "https://www.kuaishou.com/short-video/3xke2y9t4wp5fy2", "title": "斩杀线背后的资本手"}, {"url": "https://www.kuaishou.com/short-video/3x3wn5888r6eima", "title": "利比亚陆军参谋长坠机遇难"}, {"url": "https://www.kuaishou.com/short-video/3xsbrvspmby85tc", "title": "元旦倒计时8天"}, {"url": "https://www.kuaishou.com/short-video/3xn7hccpnawnmay", "title": "过年摇提前学起来"}, {"url": "https://www.kuaishou.com/short-video/3xx3uf8w6v4kdti", "title": "掘金vs独行侠"}, {"url": "https://www.kuaishou.com/short-video/3xrs5yybspsra2q", "title": "金价暴涨有人刚买就赚了"}, {"url": "https://www.kuaishou.com/short-video/3xedzbbhq2drhyc", "title": "鞠婧祎 我会找到逆转时间的公式"}, {"url": "https://www.kuaishou.com/short-video/3xb3rb8phxhpm56", "title": "兰亭序翻唱"}, {"url": "https://www.kuaishou.com/short-video/3x8xpy55bwf6fii", "title": "快手冰钓英雄挑战赛倒计时3天"}, {"url": "https://www.kuaishou.com/short-video/3xjuj5xsec95hg6", "title": "当你唱了一首不一样的伤感歌"}, {"url": "https://www.kuaishou.com/short-video/3xaz4nzr6mr5qw4", "title": "习近平对中央企业工作作出指示"}, {"url": "https://www.kuaishou.com/short-video/3xdvxkkv3w8g9s2", "title": "2025年中国交通出行超660亿人次"}, {"url": "https://www.kuaishou.com/short-video/3xq3pgtw4ti7wd2", "title": "国台办回应台当局恐吓言论"}, {"url": "https://www.kuaishou.com/short-video/3xqesthd8v9323y", "title": "江西车辆坠塘案附近村民回忆"}, {"url": "https://www.kuaishou.com/short-video/3xyqn37sbjhb5n6", "title": "女子擅闯在建隧道拍氛围照"}, {"url": "https://www.kuaishou.com/short-video/3xrthmbpkz6xxqe", "title": "原来美剧演的都是现实"}, {"url": "https://www.kuaishou.com/short-video/3xw8i3bebpnw9us", "title": "杭州上海打破最晚入冬纪录"}, {"url": "https://www.kuaishou.com/short-video/3xfzebjtuxm36n9", "title": "杀害发小妻儿凶手庭审画面曝光"}, {"url": "https://www.kuaishou.com/short-video/3xdz2m22vhafhim", "title": "深圳新闻网质疑小红书无理由屏蔽"}, {"url": "https://www.kuaishou.com/short-video/3xsxacd4pisw3f9", "title": "日本民众：高市不具政治家资质"}, {"url": "https://www.kuaishou.com/short-video/3xqhbgk9ckgt4w9", "title": "江西落水事故多名儿童遇难"}, {"url": "https://www.kuaishou.com/short-video/3xmt8r74dw6s5vs", "title": "国台办回应征集台居民违法线索"}, {"url": "https://www.kuaishou.com/short-video/3xe6mcx3istirny", "title": "警方悬赏台湾居民简文昇陈顺进"}, {"url": "https://www.kuaishou.com/short-video/3xbcc9j58gyhwec", "title": "斩杀线背后的资本手"}, {"url": "https://www.kuaishou.com/short-video/3x3mnmfxtns9aiu", "title": "李凯尔国籍已改回美国"}, {"url": "https://www.kuaishou.com/short-video/3xiieeryn2rvim6", "title": "彭庆恩：个别日本政客痴人说梦"}, {"url": "https://www.kuaishou.com/short-video/3xxvfkrbveyjd5g", "title": "韩国高中球王黄宇彬入驻快手"}, {"url": "https://www.kuaishou.com/short-video/3xe9yhj5tf7dat4", "title": "渤海发现第7个亿吨级油田"}, {"url": "https://www.kuaishou.com/short-video/3xcyg75fkyufuew", "title": "二人转神曲"}, {"url": "https://www.kuaishou.com/short-video/3xhbqxfezffahmu", "title": "美国斩杀线有多残酷"}, {"url": "https://www.kuaishou.com/short-video/3xne4ae4hy5g269", "title": "你是沙漠我是鱼广场舞"}, {"url": "https://www.kuaishou.com/short-video/3xpdbe4iu6hymtq", "title": "上门装防诈盒子骗局"}, {"url": "https://www.kuaishou.com/short-video/3xvhdgqh2sf539c", "title": "梅西印度行入账9.9亿卢比"}, {"url": "https://www.kuaishou.com/short-video/3xcn4c9fyyupbv2", "title": "黄金白银暴涨背后逻辑"}, {"url": "https://www.kuaishou.com/short-video/3x8z4dfy5cvfwmq", "title": "中美赛博对账多真实"}, {"url": "https://www.kuaishou.com/short-video/3x3an97kvua2i4c", "title": "做好农村老党员生活补贴发放工作"}, {"url": "https://www.kuaishou.com/short-video/3x8jp2r9cs4956k", "title": "何穗称生娃不存在取舍牺牲"}, {"url": "https://www.kuaishou.com/short-video/3x2ymu5k98dqtk4", "title": "特纳大帽内姆布哈德"}, {"url": "https://www.kuaishou.com/short-video/3xu9gcjv2ekjxus", "title": "长津湖战役胜利纪念日"}, {"url": "https://www.kuaishou.com/short-video/3xsfch2nr65nf7g", "title": "爱泼斯坦案大批文件曝光"}, {"url": "https://www.kuaishou.com/short-video/3x67u8rdqbanhue", "title": "乒超总决赛倒计时2天"}, {"url": "https://www.kuaishou.com/short-video/3xr4tmsekrbra24", "title": "湘超为什么这么火"}, {"url": "https://www.kuaishou.com/short-video/3xttwymrast7g7g", "title": "王小平受贿案二审宣判"}, {"url": "https://www.kuaishou.com/short-video/3xmghkqcscvmgsq", "title": "京东回应法国仓库失窃事件"}, {"url": "https://www.kuaishou.com/short-video/3x5vkp28ekfphx9", "title": "渤海发现第7个亿吨级油田"}, {"url": "https://www.kuaishou.com/short-video/3xpqwhjzzwcym3k", "title": "12岁女孩被虐待致死案改判"}, {"url": "https://www.kuaishou.com/short-video/3xhhiapmuwc5fse", "title": "钧正平警告日本军国主义"}, {"url": "https://www.kuaishou.com/short-video/3xb7hvzipy3bies", "title": "江西车辆落水事故致8人死亡"}, {"url": "https://www.kuaishou.com/short-video/3xi2w6hd7yzckzk", "title": "中国代表在安理会连说5个反对"}, {"url": "https://www.kuaishou.com/short-video/3x623ygtsk3egkc", "title": "伊朗在安理会感谢中国"}, {"url": "https://www.kuaishou.com/short-video/3x3ca9c9f3g9dnm", "title": "隐藏式门把手带来哪些安全隐患"}, {"url": "https://www.kuaishou.com/short-video/3xf3pe9x9m8baj4", "title": "曝英伟达春节前对华交付H200芯片"}, {"url": "https://www.kuaishou.com/short-video/3xf9wfrbyjc3ihw", "title": "美国两起世纪悬案迎历史性突破"}, {"url": "https://www.kuaishou.com/short-video/3xy82w6gi2m9xfs", "title": "日本发生含放射性水泄漏事件"}, {"url": "https://www.kuaishou.com/short-video/3xdvv24qtarhum2", "title": "利比亚陆军参谋长坠机遇难"}, {"url": "https://www.kuaishou.com/short-video/3xzg5xyuaakuefm", "title": "23岁大学生失联9天后遗体被发现"}, {"url": "https://www.kuaishou.com/short-video/3xfkcztv8ee3549", "title": "长征十二号甲火箭回收失败"}, {"url": "https://www.kuaishou.com/short-video/3xa6z2baiemn526", "title": "闫妮再现微醺场面"}, {"url": "https://www.kuaishou.com/short-video/3xcvsbjq9zi6xje", "title": "中国公民暂勿前往柬泰边境地区"}, {"url": "https://www.kuaishou.com/short-video/3x5z8e6wk9g5d32", "title": "现货黄金首次升破4500美元"}, {"url": "https://www.kuaishou.com/short-video/3x6pvniicp87kkk", "title": "俄25岁空姐遭41岁前夫跟踪后杀害"}, {"url": "https://www.kuaishou.com/short-video/3x859yzqihf96c2", "title": "警惕日本军舰也在“下饺子”"}, {"url": "https://www.kuaishou.com/short-video/3x6dm85uyscpf8m", "title": "第一视角跟随海警缉拿海上毒贩"}, {"url": "https://www.kuaishou.com/short-video/3xqz8cniu9ige8e", "title": "老人要求从养老院回家遭拒后自杀"}, {"url": "https://www.kuaishou.com/short-video/3xzf5r3memr7e6q", "title": "金价大涨有平台下架10克金条"}, {"url": "https://www.kuaishou.com/short-video/3xrdwbrjkdqpe9y", "title": "日本很多遗孤被亲生父母拒认"}, {"url": "https://www.kuaishou.com/short-video/3xd44hwavtmuqq6", "title": "福建女商人林惠荣再审改判无罪"}, {"url": "https://www.kuaishou.com/short-video/3xhjatckqf95vue", "title": "萝卜纸巾是什么梗"}, {"url": "https://www.kuaishou.com/short-video/3xs5dtf7jfchchg", "title": "江西车辆落水事故致8人死亡"}, {"url": "https://www.kuaishou.com/short-video/3x2twhb2heqkrxc", "title": "农业农村部进一步规范农药管理"}, {"url": "https://www.kuaishou.com/short-video/3xmpavgizzg2vh6", "title": "哦齁齁齁是什么梗"}, {"url": "https://www.kuaishou.com/short-video/3xdi7jz3s8mphng", "title": "我们不说包的"}, {"url": "https://www.kuaishou.com/short-video/3xjzj5rugwdj7q4", "title": "我只在乎你"}, {"url": "https://www.kuaishou.com/short-video/3xtm3td2bw2etni", "title": "这首歌唱给你听手势舞"}, {"url": "https://www.kuaishou.com/short-video/3x9g9adfctx7chs", "title": "冬季洗澡误区需警惕"}, {"url": "https://www.kuaishou.com/short-video/3xdfxn4jtbsnnie", "title": "睡前2分钟变美瘦脸操"}, {"url": "https://www.kuaishou.com/short-video/3x8uy955b7xv8dw", "title": "田震时隔24年再开演唱会"}, {"url": "https://www.kuaishou.com/short-video/3xbkq9z2i77te5m", "title": "中方回应乌拟制裁中国公民"}, {"url": "https://www.kuaishou.com/short-video/3xbp8vybd493seq", "title": "上海一搅拌车不慎撞塌围墙致2死"}, {"url": "https://www.kuaishou.com/short-video/3xajzut9b2t2jqk", "title": "男子带执法人员举报商家反遭群殴"}, {"url": "https://www.kuaishou.com/short-video/3xeqz2dnmzkq36s", "title": "你一句好胖我再也没有好好吃过饭"}, {"url": "https://www.kuaishou.com/short-video/3x2ee7qje4d34ym", "title": "日本核反应堆泄漏水量约为20毫升"}, {"url": "https://www.kuaishou.com/short-video/3xus63uex6ur67y", "title": "上海一工地发生事故致2人身亡"}, {"url": "https://www.kuaishou.com/short-video/3xjdnyicgqed2b9", "title": "中国驻柬使馆再次提醒尽快撤离"}, {"url": "https://www.kuaishou.com/short-video/3xtp5krr5svstb4", "title": "山西曝光9起劳动保障违法案件"}, {"url": "https://www.kuaishou.com/short-video/3x6hik5exfibeuq", "title": "小学生作业丢失被老师打至轻微伤"}, {"url": "https://www.kuaishou.com/short-video/3x56imtwzrm9avu", "title": "奶油苹果糖热量等同3碗米饭"}, {"url": "https://www.kuaishou.com/short-video/3xeedb96qvszwzk", "title": "坚决反对日本拥核"}, {"url": "https://www.kuaishou.com/short-video/3xi42apvpi4biqu", "title": "日本多名教职人员涉性犯罪受惩处"}, {"url": "https://www.kuaishou.com/short-video/3xranjsmtjifb5a", "title": "中方要求柬泰保障中国公民安全"}, {"url": "https://www.kuaishou.com/short-video/3xfqr36sds99g66", "title": "红色高跟鞋混剪版"}, {"url": "https://www.kuaishou.com/short-video/3xg5nu6xmwn2p7w", "title": "日本遗孤中井玲子痛哭身世"}, {"url": "https://www.kuaishou.com/short-video/3xpfnsqukengsq9", "title": "柬埔寨超过54万人流离失所"}, {"url": "https://www.kuaishou.com/short-video/3x957bv4i3usgbg", "title": "江苏成立调查组彻查南博事件"}, {"url": "https://www.kuaishou.com/short-video/3x4iefe9nvygbzi", "title": "长春裹上厚厚的“白绒毯”"}, {"url": "https://www.kuaishou.com/short-video/3xzheemyf7by8s4", "title": "全网最励志的脑瘫女孩"}, {"url": "https://www.kuaishou.com/short-video/3xsktj8c65ne6wi", "title": "父亲死刑后陈昌雨的人生才刚开始"}, {"url": "https://www.kuaishou.com/short-video/3xuc7zpustdmyu2", "title": "缅甸持续清理电诈据点"}, {"url": "https://www.kuaishou.com/short-video/3xx82y57xf4bnhc", "title": "美国拖欠联合国会费15亿"}, {"url": "https://www.kuaishou.com/short-video/3xedzjhq8knpzrg", "title": "莫言说作家是被耽误的脱口秀演员"}, {"url": "https://www.kuaishou.com/short-video/3xv7ymd4jzig7jy", "title": "白鹿复刻范丞丞短剧演绎"}, {"url": "https://www.kuaishou.com/short-video/3xc2txeb4dgs4tu", "title": "男子舍命阻止台北袭击案嫌犯伤人"}, {"url": "https://www.kuaishou.com/short-video/3x3i59n25d22zim", "title": "金价年内涨幅超64%"}, {"url": "https://www.kuaishou.com/short-video/3xsmwmcx35mxk66", "title": "消费者投诉伊利牛奶喝出酸腐味"}, {"url": "https://www.kuaishou.com/short-video/3x42d3sqj2dgnh9", "title": "云南丽江公开发函喊话"}, {"url": "https://www.kuaishou.com/short-video/3xur5xdvnusuxfa", "title": "12306回应高铁B座宽度争议"}, {"url": "https://www.kuaishou.com/short-video/3xcfh2izjg44ib2", "title": "韩国商业运载火箭发射升空后起火"}, {"url": "https://www.kuaishou.com/short-video/3x6jdikvkg8ztdw", "title": "泰军拆除柬埔寨地区印度教神像"}, {"url": "https://www.kuaishou.com/short-video/3xg3nukdpemptb2", "title": "工作人员回应AI疑似植入医疗广告"}, {"url": "https://www.kuaishou.com/short-video/3xn9ecbrgfsbh22", "title": "违法添加一滴香问题显著改善"}, {"url": "https://www.kuaishou.com/short-video/3xadzqa2nqcmtak", "title": "中方回应中国公民因柬泰冲突受伤"}, {"url": "https://www.kuaishou.com/short-video/3xp2qkwzam6pciu", "title": "黄金巨头金雅福70亿理财爆雷"}, {"url": "https://www.kuaishou.com/short-video/3xcwawzkg9gpdgg", "title": "上班时的窝囊心眼子"}, {"url": "https://www.kuaishou.com/short-video/3xwu34nddmzyhhu", "title": "iPhone18系列即将量产"}, {"url": "https://www.kuaishou.com/short-video/3xww9q3sgt42hea", "title": "骗子卖几万元的抗衰药就是维C"}, {"url": "https://www.kuaishou.com/short-video/3x5rqdrs4zq8kfq", "title": "美国飞行员发现不明飞行物"}, {"url": "https://www.kuaishou.com/short-video/3x2nyeqdbsri8n2", "title": "英国运河塌陷河水漏光"}, {"url": "https://www.kuaishou.com/short-video/3x8t2ic6frfmtes", "title": "韩美娟官宣恋情"}, {"url": "https://www.kuaishou.com/short-video/3xjndzfwqvrprwi", "title": "苹果公司被罚约9860万欧元"}, {"url": "https://www.kuaishou.com/short-video/3x3tqig9c7fsthg", "title": "台北袭击事件行凶者父母下跪道歉"}, {"url": "https://www.kuaishou.com/short-video/3xz2zvdqxyjhphw", "title": "蛋神开公司了"}, {"url": "https://www.kuaishou.com/short-video/3xfz99gcxnabryi", "title": "泰柬边境冲突已致泰方60人死亡"}, {"url": "https://www.kuaishou.com/short-video/3x9qikb89humj6q", "title": "大疆回应被美方列入受管制清单"}, {"url": "https://www.kuaishou.com/short-video/3xgidtcakncre5y", "title": "游戏玩家复刻福建舰被央视点赞"}, {"url": "https://www.kuaishou.com/short-video/3xngwnfysrj34c4", "title": "为弟追凶27年案一审宣判"}, {"url": "https://www.kuaishou.com/short-video/3x8xhq2y3nh7x5u", "title": "2026高速服务区建超1万个充电枪"}, {"url": "https://www.kuaishou.com/short-video/3xej3we7f2k9hz4", "title": "国内首档50+熟龄恋综将开播"}, {"url": "https://www.kuaishou.com/short-video/3xg3fnrzwg6wnxi", "title": "虞书欣何与被起哄亲一个"}, {"url": "https://www.kuaishou.com/short-video/3x8rgg57ysfsifq", "title": "广东女足2比1战胜江苏无锡女足"}, {"url": "https://www.kuaishou.com/short-video/3xhap4ciu3y68dq", "title": "鞠婧祎美貌震撼视觉"}, {"url": "https://www.kuaishou.com/short-video/3xsy3va7fknqvb2", "title": "桀骜不驯的性格其实没改"}, {"url": "https://www.kuaishou.com/short-video/3x5uqcc5nuxiiqe", "title": "沈阳的雪下老大了"}, {"url": "https://www.kuaishou.com/short-video/3x96pc2j49b7kry", "title": "老人要求从养老院回家遭拒后自杀"}, {"url": "https://www.kuaishou.com/short-video/3xaukq2a8amywne", "title": "圣诞氛围感美甲"}, {"url": "https://www.kuaishou.com/short-video/3xy9jct2za835a2", "title": "俄中将被炸身亡如何影响俄乌局势"}, {"url": "https://www.kuaishou.com/short-video/3xnpg3wup5exd2k", "title": "卡了电竞是什么梗"}, {"url": "https://www.kuaishou.com/short-video/3xz54xn4wagz5ck", "title": "运毒抛货全过程视频曝光"}, {"url": "https://www.kuaishou.com/short-video/3xr2gxq8hxcgs22", "title": "俄中关系达历史最高水平"}, {"url": "https://www.kuaishou.com/short-video/3xjyr3mimu9bk96", "title": "大正二胎母子平安"}, {"url": "https://www.kuaishou.com/short-video/3xn794b9ubx9s5i", "title": "勇士120比97大胜魔术"}, {"url": "https://www.kuaishou.com/short-video/3xbehvs65tys3z6", "title": "成飞研究员讲述中国航空逆袭传奇"}, {"url": "https://www.kuaishou.com/short-video/3xgx4pana5j84eu", "title": "俄乌冲突现场光纤密如蛛网"}, {"url": "https://www.kuaishou.com/short-video/3xfyecqyenc4m6q", "title": "解读台海局势下的美日布局"}, {"url": "https://www.kuaishou.com/short-video/3xhvxsucagucycu", "title": "泰军装甲车编队向柬埔寨阵地推进"}, {"url": "https://www.kuaishou.com/short-video/3xdhvavuwwvuuny", "title": "圣诞树拼豆图纸"}, {"url": "https://www.kuaishou.com/short-video/3x2g3ugcppri9e4", "title": "赵露思ADD男团合拍"}, {"url": "https://www.kuaishou.com/short-video/3x6f2s6n4azv2ja", "title": "医保余额年底不清零"}, {"url": "https://www.kuaishou.com/short-video/3xevv6bqtg3ap6a", "title": "美国斩杀线"}, {"url": "https://www.kuaishou.com/short-video/3xuk5h3wsyedp3y", "title": "贵州一枝花"}, {"url": "https://www.kuaishou.com/short-video/3xjwu6n6hqisshm", "title": "美国少年偷车飙车被捕"}, {"url": "https://www.kuaishou.com/short-video/3xdc4zfzdcwj29q", "title": "宗馥莉与宗家三兄妹相关案件开庭"}, {"url": "https://www.kuaishou.com/short-video/3xrvmkfpfppm3w6", "title": "萝卜纸巾猫咪挑战"}, {"url": "https://www.kuaishou.com/short-video/3xa3q9hh28t9k2y", "title": "山东人眼里的山楂树下"}, {"url": "https://www.kuaishou.com/short-video/3xre9yqzb56t2s6", "title": "金声奖金句盘点"}, {"url": "https://www.kuaishou.com/short-video/3xh2kq6gc8gkhiu", "title": "沙溢给综艺大牛马当摄像"}, {"url": "https://www.kuaishou.com/short-video/3x2uneq7qsecnq4", "title": "印度德里空气污染严重"}, {"url": "https://www.kuaishou.com/short-video/3x88thu2fuaziue", "title": "每发射3枚火箭就有1枚来自中国"}, {"url": "https://www.kuaishou.com/short-video/3xb45bkdxfhpd3s", "title": "醉驾撞死女教师案家属抗诉被驳回"}, {"url": "https://www.kuaishou.com/short-video/3xpd57ieiqpprmg", "title": "住建部研判未来五年楼市新趋势"}, {"url": "https://www.kuaishou.com/short-video/3x9wt8w788bvjh2", "title": "乌克兰博主穿新疆非遗服饰"}, {"url": "https://www.kuaishou.com/short-video/3xb2bf2rksapwvk", "title": "交通运输部推行规范化执法"}, {"url": "https://www.kuaishou.com/short-video/3xt53updvsky9bw", "title": "当你帮家里卖水果"}, {"url": "https://www.kuaishou.com/short-video/3x6khi8ciryzphg", "title": "常思思高音震撼超级老声"}, {"url": "https://www.kuaishou.com/short-video/3xjtaiu7vrqmyvg", "title": "外交部称美方炒作是其一贯伎俩"}, {"url": "https://www.kuaishou.com/short-video/3xmkb8qwcuzhvu6", "title": "樊振东或缺席乒超总决赛"}, {"url": "https://www.kuaishou.com/short-video/3xguadejhigx4da", "title": "世界品牌500强中国数量再超日本"}, {"url": "https://www.kuaishou.com/short-video/3xqg5qqpneh872m", "title": "曼波也来认萝卜纸巾了"}, {"url": "https://www.kuaishou.com/short-video/3xv8v75u83ahnni", "title": "司马光教suk跳舞地狱级难度"}]