[{"url": "https://www.kuaishou.com/short-video/3xr4n888wwfma4w", "title": "第十三批志愿军烈士遗骸回国"}, {"url": "https://www.kuaishou.com/short-video/3x46xi2qnqihbye", "title": "共和国最能打的一批人回来了"}, {"url": "https://www.kuaishou.com/short-video/3xn3y7mc8s7mifu", "title": "老兵含泪呼唤“哥哥我好想你们”"}, {"url": "https://www.kuaishou.com/short-video/3xd5ajnhewiyrhk", "title": "一季度规上工业增加值实现正增长"}, {"url": "https://www.kuaishou.com/short-video/3xr79gqddmt678m", "title": "日本女主播遇地震一秒变脸"}, {"url": "https://www.kuaishou.com/short-video/3xtvfjtvmm68h89", "title": "辽宁8岁男孩发现金矿线索"}, {"url": "https://www.kuaishou.com/short-video/3xkmx8zqk5wtr3a", "title": "日本自卫队弹药爆炸已致3人死亡"}, {"url": "https://www.kuaishou.com/short-video/3x5yx372n6gxsdi", "title": "沃尔玛或获百亿美元关税退款"}, {"url": "https://www.kuaishou.com/short-video/3x9ibbppk98yws2", "title": "警惕零食伪装新型毒品"}, {"url": "https://www.kuaishou.com/short-video/3xmy8vcvi374ey6", "title": "坚决抵制日本新型军国主义妄动"}, {"url": "https://www.kuaishou.com/short-video/3xd5pqyxpig92v6", "title": "中国军舰南海实弹射击"}, {"url": "https://www.kuaishou.com/short-video/3xuj5c94tpe9rik", "title": "张治中将军女儿张素久逝世"}, {"url": "https://www.kuaishou.com/short-video/3xq4fqdsvujc6z4", "title": "国内油价将迎今年首次下调"}, {"url": "https://www.kuaishou.com/short-video/3xj3kcuvu6ebmiu", "title": "日本地震引发多地海啸"}, {"url": "https://www.kuaishou.com/short-video/3xsycansxh6rq3g", "title": "宋晓峰发起春耕农机争霸赛"}, {"url": "https://www.kuaishou.com/short-video/3xdn5msh28yzj9i", "title": "李小冉被老天爷追着喂饭吃的人生"}, {"url": "https://www.kuaishou.com/short-video/3xzf8d7skzt3mu4", "title": "严禁向未成年人提供虚拟亲密关系"}, {"url": "https://www.kuaishou.com/short-video/3xzkfbbr65k3gys", "title": "华为真的太会选代言人了"}, {"url": "https://www.kuaishou.com/short-video/3xj9w3yw3xukg5k", "title": "张雪车队F4中国赛夺冠"}, {"url": "https://www.kuaishou.com/short-video/3xvw6hnuymbkxy6", "title": "五一航班大面积取消"}, {"url": "https://www.kuaishou.com/short-video/3xbxci75ph4u24q", "title": "万物皆有灵性 母爱不分物种"}, {"url": "https://www.kuaishou.com/short-video/3xqmf7d4mwg9wfe", "title": "老铁谈3岁男童被虐致死案"}, {"url": "https://www.kuaishou.com/short-video/3xgdtizz6mgqr6s", "title": "“荣归50、红鹰”接英雄回家"}, {"url": "https://www.kuaishou.com/short-video/3xzw45upe43aszq", "title": "木兰姐姐报名春耕农机争霸赛"}, {"url": "https://www.kuaishou.com/short-video/3x6nyxmndxrqmgw", "title": "当iPhone遇上OPhone"}, {"url": "https://www.kuaishou.com/short-video/3xtqek5kquqpkug", "title": "温峥嵘阚清子 听劝"}, {"url": "https://www.kuaishou.com/short-video/3xee7x5ns99zsxu", "title": "印度男子晕倒栽进泳池无人施救"}, {"url": "https://www.kuaishou.com/short-video/3xurdaustpqrst9", "title": "库克卸任意味着什么"}, {"url": "https://www.kuaishou.com/short-video/3xjjf8mrz8zz2za", "title": "孙颖莎同款OPPOfindx9spro"}, {"url": "https://www.kuaishou.com/short-video/3xaiezgn55kchus", "title": "鸿蒙6.1系统更新"}, {"url": "https://www.kuaishou.com/short-video/3xpsp8ikkhprcvc", "title": "全球变暖会导致什么"}, {"url": "https://www.kuaishou.com/short-video/3x38wr2jzud9e26", "title": "多家知名药店连环套骗取医保基金"}, {"url": "https://www.kuaishou.com/short-video/3xgzk967mcpmste", "title": "法院回应男童被虐致死案量刑依据"}, {"url": "https://www.kuaishou.com/short-video/3xpv7udiq8z4xgq", "title": "华为首款AI眼镜来了"}, {"url": "https://www.kuaishou.com/short-video/3x3c827yvz36p8e", "title": "日本拟投万亿日元回收资源"}, {"url": "https://www.kuaishou.com/short-video/3xuen5wffmj8wmg", "title": "黄大发涉黑案一审宣判"}, {"url": "https://www.kuaishou.com/short-video/3xkb6cvs28em2ry", "title": "第十三批烈士遗骸回国安排公布"}, {"url": "https://www.kuaishou.com/short-video/3xrdpq254x275se", "title": "华为星钻手镯表官宣"}, {"url": "https://www.kuaishou.com/short-video/3x7cdm8rbyn79wk", "title": "宁夏启动沙漠化治理项目"}, {"url": "https://www.kuaishou.com/short-video/3xtx69qqqw7ksu9", "title": "陈紫函跳小鸡舞"}, {"url": "https://www.kuaishou.com/short-video/3xsk5tyvg74zqx6", "title": "中国早已不再是131年前的中国"}, {"url": "https://www.kuaishou.com/short-video/3xwqrc9pjtm2vhy", "title": "失控进化鸿蒙版即将开测"}, {"url": "https://www.kuaishou.com/short-video/3xmituhezg8v3x9", "title": "日本强震狗狗淡定睡觉"}, {"url": "https://www.kuaishou.com/short-video/3xr8nf5ei2uem9g", "title": "带100位志愿军老兵接战友回家"}, {"url": "https://www.kuaishou.com/short-video/3xzihnzud9gi6hi", "title": "瑶一瑶跳扫地摇"}, {"url": "https://www.kuaishou.com/short-video/3xwq52kuh58n5qy", "title": "华为Pura X Max太阔了"}, {"url": "https://www.kuaishou.com/short-video/3xr6ncw3svp5yc2", "title": "代露娃误闯天家下一秒登山"}, {"url": "https://www.kuaishou.com/short-video/3x9nq49xp4p4u5c", "title": "乌兰图雅随地大小睡"}, {"url": "https://www.kuaishou.com/short-video/3xgn4ci5cfuw4ii", "title": "跟随朱一龙走进青海祁连山"}, {"url": "https://www.kuaishou.com/short-video/3xc9vdsftsarjhw", "title": "日本自卫队弹药爆炸已致3人死亡"}, {"url": "https://www.kuaishou.com/short-video/3x37ca872ywgfu9", "title": "海伦市全民阅读活动周"}, {"url": "https://www.kuaishou.com/short-video/3xi94nehbnf9ftc", "title": "日本东北海域7.7级地震"}, {"url": "https://www.kuaishou.com/short-video/3xb4uxjcm23n7jq", "title": "瑶一瑶误闯天家挑战"}, {"url": "https://www.kuaishou.com/short-video/3x2c8zewxsajcm4", "title": "青海门源雪山风筝飞扬"}, {"url": "https://www.kuaishou.com/short-video/3x4ysnsq3suargu", "title": "JHH摇"}, {"url": "https://www.kuaishou.com/short-video/3x8tdpbg4mg5sey", "title": "刘德华女儿奴实锤"}, {"url": "https://www.kuaishou.com/short-video/3xgi4rx23zrinx6", "title": "闽超票根享餐饮折扣"}, {"url": "https://www.kuaishou.com/short-video/3xzeb6c9djanndk", "title": "美军公布强登伊朗货船画面"}, {"url": "https://www.kuaishou.com/short-video/3xjtpsahvjq2n59", "title": "李小冉因跑调哭了2晚上"}, {"url": "https://www.kuaishou.com/short-video/3x3tjdemdat87bk", "title": "警方通报长治一女子坠楼身亡"}, {"url": "https://www.kuaishou.com/short-video/3xdw6f7vsumgg69", "title": "AI演员拍的戏就应该找AI观众看"}, {"url": "https://www.kuaishou.com/short-video/3xeycn5zu26ga2s", "title": "沈梦辰连续4年做热玛吉"}, {"url": "https://www.kuaishou.com/short-video/3xn2zarin8rypgg", "title": "云养一只咕咕嘎嘎"}, {"url": "https://www.kuaishou.com/short-video/3xc7j7ryu2stdhw", "title": "外国人热议北京机器人半马"}, {"url": "https://www.kuaishou.com/short-video/3xsdddeag6ijkea", "title": "林依轮爱情鸟舞蹈变装版"}, {"url": "https://www.kuaishou.com/short-video/3xb7tae8czeqk2i", "title": "我又泪流满面你不在我身边"}, {"url": "https://www.kuaishou.com/short-video/3xi74zvrwzz2yue", "title": "盗墓笔记十年人间"}, {"url": "https://www.kuaishou.com/short-video/3xgwpmbep5vbfbi", "title": "他们说快写一首情歌雅俗共赏"}, {"url": "https://www.kuaishou.com/short-video/3x6je7ycss9wkfw", "title": "律师解读男童被虐致死案判罚"}, {"url": "https://www.kuaishou.com/short-video/3x779r3a6apneqy", "title": "平台回应女孩千万公款打赏主播"}, {"url": "https://www.kuaishou.com/short-video/3xe8wbiktipriia", "title": "蜕蝶陈姝君还是太权威了"}, {"url": "https://www.kuaishou.com/short-video/3xpe8z8e5qwkdgw", "title": "伊朗不参加谈判的决定尚未改变"}, {"url": "https://www.kuaishou.com/short-video/3xufpjwzwk7uwdq", "title": "华为Pura90 Pro Max有多强"}, {"url": "https://www.kuaishou.com/short-video/3xw6q87exs8ap7e", "title": "日本东北海域地震居民生活实拍"}, {"url": "https://www.kuaishou.com/short-video/3x2vg29fmtj6cw6", "title": "红米K90Max发布会定档今晚7点"}, {"url": "https://www.kuaishou.com/short-video/3xcnscfz4zd446c", "title": "习近平同沙特王储兼首相通电话"}, {"url": "https://www.kuaishou.com/short-video/3xuzp9in2waqy2y", "title": "日本7.7级地震现场画面"}, {"url": "https://www.kuaishou.com/short-video/3xbefsjtdym6tiu", "title": "让读书成为一种生活方式"}, {"url": "https://www.kuaishou.com/short-video/3xxb5ti6wu6vgfk", "title": "女子虐死男友3岁儿子被判死缓"}, {"url": "https://www.kuaishou.com/short-video/3xc8px569gcwhjk", "title": "男童被虐致死案将宣判生母发声"}, {"url": "https://www.kuaishou.com/short-video/3xj46brwr88vceq", "title": "巴西总统谴责美国封锁古巴"}, {"url": "https://www.kuaishou.com/short-video/3xvkcpixw3tuu7y", "title": "非门小小吴可爱变装"}, {"url": "https://www.kuaishou.com/short-video/3xd7h7i656hgmqy", "title": "周亮被免职"}, {"url": "https://www.kuaishou.com/short-video/3xm3c5w8ewmvgk9", "title": "中国代表当场驳斥美方攻击抹黑"}, {"url": "https://www.kuaishou.com/short-video/3x2yi4pwha3afu2", "title": "女孩挪用1700万打赏主播"}, {"url": "https://www.kuaishou.com/short-video/3xj6is333um585i", "title": "西班牙加区主席欢迎中国投资"}, {"url": "https://www.kuaishou.com/short-video/3xs2m7nw8qqhbfe", "title": "单亲妈妈带孩子搬进毛坯房后哭了"}, {"url": "https://www.kuaishou.com/short-video/3xk2m4tkg5fkn6k", "title": "日本正式允许出口杀伤性武器"}, {"url": "https://www.kuaishou.com/short-video/3xgqk7vgvznr39g", "title": "邓紫棋患地中海贫血"}, {"url": "https://www.kuaishou.com/short-video/3xpqy56grc5nnvk", "title": "李维嘉沈梦辰天津盘头"}, {"url": "https://www.kuaishou.com/short-video/3xivvbfspvwzxfs", "title": "平安银行辟谣管理层变动"}, {"url": "https://www.kuaishou.com/short-video/3xcm49g7yvi3pp9", "title": "印度拟对苹果罚款380亿"}, {"url": "https://www.kuaishou.com/short-video/3xcy6mijg9pjjwq", "title": "赵丽颖38岁状态"}, {"url": "https://www.kuaishou.com/short-video/3xmanv9c4tt85mq", "title": "都市丽人就小地雷事件致歉"}, {"url": "https://www.kuaishou.com/short-video/3x5y6sygrsmw77i", "title": "特朗普解职劳工部长"}, {"url": "https://www.kuaishou.com/short-video/3xa88xchai4ixsg", "title": "日本强震最新画面曝光"}, {"url": "https://www.kuaishou.com/short-video/3xbfufdpmjk96ry", "title": "华晨宇火星乐园2.0亮相"}, {"url": "https://www.kuaishou.com/short-video/3x2ie98377u276c", "title": "印度客车坠崖21死29伤"}, {"url": "https://www.kuaishou.com/short-video/3xrcyeut6zvaahs", "title": "卢拉称南非须出席G20"}, {"url": "https://www.kuaishou.com/short-video/3xew27kqp9nqqgk", "title": "运20B最高标准接迎英烈回家"}, {"url": "https://www.kuaishou.com/short-video/3xai6spkcpd4zae", "title": "哇哦Mrbeast"}, {"url": "https://www.kuaishou.com/short-video/3xvrakpzm5ra69c", "title": "美官员为特朗普战争罪辩护"}, {"url": "https://www.kuaishou.com/short-video/3xhytp2fsccir9a", "title": "日本学者：南海若地震日本将崩溃"}, {"url": "https://www.kuaishou.com/short-video/3x4azz9vn86u89k", "title": "特纳斯将接任苹果CEO"}, {"url": "https://www.kuaishou.com/short-video/3xett6fjn4h8nn6", "title": "泰安警方普法反跨境赌博"}, {"url": "https://www.kuaishou.com/short-video/3xuhk42gbj7z3fw", "title": "爱奇艺创始人强调科技为人服务"}, {"url": "https://www.kuaishou.com/short-video/3xemcu8d3y9hspq", "title": "“三个不相信”的杨根思英雄精神"}, {"url": "https://www.kuaishou.com/short-video/3xyadeszg9rxz74", "title": "‌刘向蕙说爸爸是刘德华没人相信"}, {"url": "https://www.kuaishou.com/short-video/3x8rqde4hbv9kae", "title": "朱之文真的要去南天门"}, {"url": "https://www.kuaishou.com/short-video/3xeb29qsg8tc72a", "title": "英议员怒斥首相被逐出议会"}, {"url": "https://www.kuaishou.com/short-video/3xgxjzgp68jziec", "title": "俄图22M3轰炸机波罗的海飞行"}, {"url": "https://www.kuaishou.com/short-video/3x5nba2vdfrgi2g", "title": "赵继伟发文：呵呵"}, {"url": "https://www.kuaishou.com/short-video/3xrx574xvsye42g", "title": "走好先烈回到祖国怀抱的第一步"}, {"url": "https://www.kuaishou.com/short-video/3x3n9f6ph9uhngs", "title": "总书记引领航天强国建设"}, {"url": "https://www.kuaishou.com/short-video/3xxxeq736938xb4", "title": "我国数字阅读作品总量超7000万部"}, {"url": "https://www.kuaishou.com/short-video/3x5v9sz84pdeizs", "title": "都是一副臭皮囊卡点"}, {"url": "https://www.kuaishou.com/short-video/3xcxdgjjg7e7uai", "title": "光遇版误闯天家"}, {"url": "https://www.kuaishou.com/short-video/3xqane2jgegsdcu", "title": "今年谷雨60年一遇"}, {"url": "https://www.kuaishou.com/short-video/3xxapnsfw5ifja2", "title": "2名中国台湾游客在日本坠机身亡"}, {"url": "https://www.kuaishou.com/short-video/3xgmj5j5uvmc25k", "title": "美宾州民宅爆炸致7死"}, {"url": "https://www.kuaishou.com/short-video/3xfkm9pfupjypj9", "title": "大熊猫龇牙咧嘴瞬间破功"}, {"url": "https://www.kuaishou.com/short-video/3x86az36eiwbzak", "title": "吃饭小游戏翻车现场"}, {"url": "https://www.kuaishou.com/short-video/3x2fs32kp4wsihs", "title": "河北蠡县一农田被曝现红色地下水"}, {"url": "https://www.kuaishou.com/short-video/3x3khxnsv5mywms", "title": "网红贺冬冬称300万财物被盗"}, {"url": "https://www.kuaishou.com/short-video/3xb9uea86sh4tj6", "title": "比亚迪海狮05价格引热议"}, {"url": "https://www.kuaishou.com/short-video/3xeu3ebv2f7y2nu", "title": "雨雨摇2"}, {"url": "https://www.kuaishou.com/short-video/3xfpbwumq4xncn2", "title": "雨蝶清唱"}, {"url": "https://www.kuaishou.com/short-video/3x8vz3n7egjvihk", "title": "日本地震瞬间吊灯狂摇不止"}, {"url": "https://www.kuaishou.com/short-video/3x5p44p6gigbgaw", "title": "警方回应强奸案取保争议"}, {"url": "https://www.kuaishou.com/short-video/3xdmi7tmuykfq9w", "title": "笑梗不笑人"}, {"url": "https://www.kuaishou.com/short-video/3xmeiw66rutafgw", "title": "日本地震引发海啸不会影响我国"}, {"url": "https://www.kuaishou.com/short-video/3x2as3xhw7ga4qa", "title": "莫桑比克总统向毛泽东铜像献花"}, {"url": "https://www.kuaishou.com/short-video/3xdqdhcnrw9dhmc", "title": "广州大山遭私挖水晶破坏"}, {"url": "https://www.kuaishou.com/short-video/3xabsz8ij8aq7iw", "title": "李小冉贺峻霖你们不要再打了"}, {"url": "https://www.kuaishou.com/short-video/3xj9s57tdjxmfmg", "title": "郑丽文谈解决台湾问题的方式"}, {"url": "https://www.kuaishou.com/short-video/3x5zbpyp72was2g", "title": "2026年日本地震或更频繁"}, {"url": "https://www.kuaishou.com/short-video/3xfqvqwkqbw2f7e", "title": "华为Pura90全系价格公布"}, {"url": "https://www.kuaishou.com/short-video/3xi8cxc9hasgkdm", "title": "日本的野心远超“自卫”"}, {"url": "https://www.kuaishou.com/short-video/3xccikkqwkbfwwm", "title": "21岁王文杰破半马全国纪录"}, {"url": "https://www.kuaishou.com/short-video/3x85i6zy95jnp4q", "title": "我见识到自己的厉害了宠物版"}, {"url": "https://www.kuaishou.com/short-video/3xek8nuap6rvnue", "title": "误闯天家宠物版"}, {"url": "https://www.kuaishou.com/short-video/3xfj2h3skcpwrvm", "title": "日本可能出现3米浪高海啸"}, {"url": "https://www.kuaishou.com/short-video/3xaz7mja224r3zi", "title": "IU边佑锡新剧21世纪大君夫人"}, {"url": "https://www.kuaishou.com/short-video/3xwc33ec4rd99py", "title": "白小白献唱岳云鹏演唱会"}, {"url": "https://www.kuaishou.com/short-video/3x9npdi8ncdgpb4", "title": "胖甜误闯天家舞蹈挑战"}, {"url": "https://www.kuaishou.com/short-video/3xujzy2m7b7a3tq", "title": "上海国际旅游度假区十周年"}, {"url": "https://www.kuaishou.com/short-video/3x4ec6btinzqx5q", "title": "高市早苗向靖国神社献祭品"}, {"url": "https://www.kuaishou.com/short-video/3xz3ffq3ztrtbcu", "title": "春天就馋这口婆婆丁"}, {"url": "https://www.kuaishou.com/short-video/3xdu8sry7u6w9ba", "title": "上海大胜辽宁豪取22连胜"}, {"url": "https://www.kuaishou.com/short-video/3xyibnhzt6buya4", "title": "华为铁了心要当演唱会神机"}, {"url": "https://www.kuaishou.com/short-video/3xcv6eggc9kajm4", "title": "坏女孩翻唱"}, {"url": "https://www.kuaishou.com/short-video/3x76bqsx8kdgfne", "title": "一男子携刀进日本议员会馆被捕"}, {"url": "https://www.kuaishou.com/short-video/3xkwyjvuxz3hqig", "title": "中国海军过航横当水道回应挑衅"}, {"url": "https://www.kuaishou.com/short-video/3xzw7a5wcv6bems", "title": "华为手机后期或涨价"}, {"url": "https://www.kuaishou.com/short-video/3x3mdis5ea2nis4", "title": "伊朗拒绝参加伊美第二轮谈判"}, {"url": "https://www.kuaishou.com/short-video/3xfgfnmbnt589qk", "title": "中方直接点出日本历史罪责"}, {"url": "https://www.kuaishou.com/short-video/3x497fq3m9ckxd4", "title": "日本地震是否会对核电站产生影响"}, {"url": "https://www.kuaishou.com/short-video/3xp3tmxawzsjxni", "title": "日本超三万人在国会周边集会抗议"}, {"url": "https://www.kuaishou.com/short-video/3xqtmyuhs5v5t6k", "title": "帮闺蜜化一种很新的妆容"}, {"url": "https://www.kuaishou.com/short-video/3xjqe5nt94rm684", "title": "关中王来了又怎样"}, {"url": "https://www.kuaishou.com/short-video/3x8crfjfk23uhig", "title": "误闯天家"}, {"url": "https://www.kuaishou.com/short-video/3xsbr8im3e868ck", "title": "已经很期待拿到华为的新品了"}, {"url": "https://www.kuaishou.com/short-video/3x25xkcpqrxnqva", "title": "公婆为不吵醒母子推拖拉机数十米"}, {"url": "https://www.kuaishou.com/short-video/3xtbbb2rva24cqc", "title": "日本称正在确认核电站是否泄漏"}, {"url": "https://www.kuaishou.com/short-video/3x76knis6qizwq9", "title": "桐桐就酱拨开天空的乌云"}, {"url": "https://www.kuaishou.com/short-video/3xv4dynsjhgmjmi", "title": "吴瑞林逝世31周年"}, {"url": "https://www.kuaishou.com/short-video/3xapjd8754vf65w", "title": "近70款车集体降价"}, {"url": "https://www.kuaishou.com/short-video/3xuaxum2jvsiwyi", "title": "美国一男子枪杀7名子女"}, {"url": "https://www.kuaishou.com/short-video/3x3eyxppcnawdwc", "title": "敲冬瓜"}, {"url": "https://www.kuaishou.com/short-video/3xu5rzfky6qxjdy", "title": "莫桑比克总统查波抵达北京"}, {"url": "https://www.kuaishou.com/short-video/3xccy8mmyyczvhs", "title": "郑丽文谈解决台湾问题的方式"}, {"url": "https://www.kuaishou.com/short-video/3xde9t6hvyp99tq", "title": "隔壁阿姨给小王介绍了对象"}, {"url": "https://www.kuaishou.com/short-video/3x65h5k5z3yakge", "title": "赵心童丁俊晖上演中国德比"}, {"url": "https://www.kuaishou.com/short-video/3x6y729hhwkytw2", "title": "日本东北海域地震居民生活实拍"}, {"url": "https://www.kuaishou.com/short-video/3xgqvcmiup8je8y", "title": "00后张健获评见义勇为模范"}, {"url": "https://www.kuaishou.com/short-video/3xa5zetbc2bbj2u", "title": "用猫meme打开出马"}, {"url": "https://www.kuaishou.com/short-video/3xkyhw29qiahxf9", "title": "华为Pura90 Pro Max有多强"}, {"url": "https://www.kuaishou.com/short-video/3xn3ii9juduchri", "title": "你想不想知道我当年啊俏黄蓉版"}, {"url": "https://www.kuaishou.com/short-video/3xbef2rab45524w", "title": "单亲妈妈逃离家暴逆袭重生"}, {"url": "https://www.kuaishou.com/short-video/3xh4nat7ghkivva", "title": "中方直接点出日本历史罪责"}, {"url": "https://www.kuaishou.com/short-video/3xm4tsmyzkii3bw", "title": "上海男篮vs辽宁男篮"}, {"url": "https://www.kuaishou.com/short-video/3x9buxschky4a99", "title": "俏黄蓉为母则刚"}, {"url": "https://www.kuaishou.com/short-video/3xexr99bnsk5sca", "title": "叶童演黑社会大佬反差感拉满"}, {"url": "https://www.kuaishou.com/short-video/3xzkg9jpmpfties", "title": "女孩挪用1700万打赏主播"}, {"url": "https://www.kuaishou.com/short-video/3xx6exg6xcg24i2", "title": "鹿晗捐14座足球场"}, {"url": "https://www.kuaishou.com/short-video/3xyvmjrui3va926", "title": "猫咪表演前滚翻"}, {"url": "https://www.kuaishou.com/short-video/3xds4igccap4zxs", "title": "山东聊城妈妈语音引误会"}, {"url": "https://www.kuaishou.com/short-video/3x27q3hkuusvyts", "title": "华为Pura 90 Pro 粉红芭乐也好看"}, {"url": "https://www.kuaishou.com/short-video/3xizecev5uyahhi", "title": "遭家暴俏黄蓉离婚给了前夫25万"}, {"url": "https://www.kuaishou.com/short-video/3x5xf642g7d7mu9", "title": "日本右翼妄图拥核"}, {"url": "https://www.kuaishou.com/short-video/3xxtr55ea2anwf2", "title": "余承东见易烊千玺也紧张"}, {"url": "https://www.kuaishou.com/short-video/3xkkry9ybmcsqzq", "title": "日本东北海域地震东京震感明显"}, {"url": "https://www.kuaishou.com/short-video/3xhwk6j9i44k7s6", "title": "日本强震最新画面曝光"}, {"url": "https://www.kuaishou.com/short-video/3xi4dxft2q8i8y2", "title": "丁俊晖晋级世锦赛16强"}, {"url": "https://www.kuaishou.com/short-video/3x9qped28wd3n5u", "title": "装西瓜挑战"}, {"url": "https://www.kuaishou.com/short-video/3xcz2bcng27ytf6", "title": "21世纪大君夫人IU边佑锡CP好好磕"}, {"url": "https://www.kuaishou.com/short-video/3x6mxirmtz5xpm4", "title": "八千里路云和月老太爷演技封神"}, {"url": "https://www.kuaishou.com/short-video/3xcgrwp6zwmv5p4", "title": "EWC2026英雄联盟预选赛"}, {"url": "https://www.kuaishou.com/short-video/3xk5sz58x74yud6", "title": "爱奇艺股价暴跌"}, {"url": "https://www.kuaishou.com/short-video/3x7wqd4tg7dita6", "title": "日本东北海域地震居民生活实拍"}, {"url": "https://www.kuaishou.com/short-video/3xcjzbjwttxnpu4", "title": "日本为什么派它过航台湾海峡"}, {"url": "https://www.kuaishou.com/short-video/3xj48pfmj7unw7a", "title": "古天乐隔空亲吻宣萱郭羡妮滕丽名"}, {"url": "https://www.kuaishou.com/short-video/3xmhjcg9kh7tk2g", "title": "上海大胜辽宁豪取22连胜"}, {"url": "https://www.kuaishou.com/short-video/3xj5i56jjnedcug", "title": "大疆Pocket 4华为Pura X Max互联"}]